titlebarctk/__init__.py
titlebarctk/dat/dat_main.py
titlebarctk/dat/aud/__init__.py
titlebarctk/dat/img/ExitClose.py
titlebarctk/dat/img/FullScreen.py
titlebarctk/dat/img/Minimise.py
titlebarctk/dat/img/Save.py
titlebarctk/dat/img/__init__.py
titlebarctk-0.1.4.dist-info/LICENSE
titlebarctk-0.1.4.dist-info/METADATA
titlebarctk-0.1.4.dist-info/WHEEL
titlebarctk-0.1.4.dist-info/top_level.txt
titlebarctk-0.1.4.dist-info/RECORD
