Metadata-Version: 2.1
Name: titlebarctk
Version: 0.1.4
Summary: Create a custom title bar for a windows app developed with custom tkinter
Author-email: DevDolphin7 <devdolphin7@outlook.com>
Project-URL: Homepage, https://github.com/DevDolphin7/TitleBar
Classifier: Programming Language :: Python :: 3
Classifier: License :: OSI Approved :: GNU General Public License v3 (GPLv3)
Classifier: Operating System :: Microsoft :: Windows :: Windows 10
Requires-Python: >=3.8
License-File: LICENSE
Requires-Dist: pywin32
Requires-Dist: screeninfo
Requires-Dist: pillow
Requires-Dist: customtkinter
